{"4_frame12360.jpg562625":{"filename":"4_frame12360.jpg","size":562625,"regions":[{"shape_attributes":{"name":"rect","x":336,"y":643,"width":27,"height":10},"region_attributes":{"value":"na","type":"plate"}},{"shape_attributes":{"name":"rect","x":450,"y":700,"width":66,"height":20},"region_attributes":{"value":"na","type":"plate"}},{"shape_attributes":{"name":"rect","x":455,"y":703,"width":7,"height":11},"region_attributes":{"value":"D","type":"alphabet"}},{"shape_attributes":{"name":"rect","x":461,"y":703,"width":6,"height":12},"region_attributes":{"value":"L","type":"alphabet"}},{"shape_attributes":{"name":"rect","x":467,"y":703,"width":6,"height":12},"region_attributes":{"value":"2","type":"number"}},{"shape_attributes":{"name":"rect","x":473,"y":703,"width":6,"height":13},"region_attributes":{"value":"C","type":"alphabet"}},{"shape_attributes":{"name":"rect","x":479,"y":703,"width":5,"height":13},"region_attributes":{"value":"A","type":"alphabet"}},{"shape_attributes":{"name":"rect","x":485,"y":704,"width":4,"height":13},"region_attributes":{"value":"E","type":"alphabet"}},{"shape_attributes":{"name":"rect","x":490,"y":705,"width":5,"height":12},"region_attributes":{"value":"0","type":"number"}},{"shape_attributes":{"name":"rect","x":496,"y":705,"width":6,"height":12},"region_attributes":{"value":"4","type":"number"}},{"shape_attributes":{"name":"rect","x":502,"y":706,"width":6,"height":12},"region_attributes":{"value":"9","type":"number"}},{"shape_attributes":{"name":"rect","x":507,"y":705,"width":6,"height":13},"region_attributes":{"value":"0","type":"number"}},{"shape_attributes":{"name":"rect","x":863,"y":727,"width":115,"height":28},"region_attributes":{"value":"na","type":"plate"}},{"shape_attributes":{"name":"rect","x":872,"y":731,"width":11,"height":20},"region_attributes":{"value":"U","type":"alphabet"}},{"shape_attributes":{"name":"rect","x":883,"y":732,"width":9,"height":18},"region_attributes":{"value":"P","type":"alphabet"}},{"shape_attributes":{"name":"rect","x":893,"y":733,"width":12,"height":17},"region_attributes":{"value":"1","type":"number"}},{"shape_attributes":{"name":"rect","x":904,"y":732,"width":11,"height":18},"region_attributes":{"value":"4","type":"number"}},{"shape_attributes":{"name":"rect","x":913,"y":731,"width":13,"height":20},"region_attributes":{"value":"D","type":"alphabet"}},{"shape_attributes":{"name":"rect","x":925,"y":731,"width":11,"height":20},"region_attributes":{"value":"D","type":"alphabet"}},{"shape_attributes":{"name":"rect","x":934,"y":731,"width":12,"height":19},"region_attributes":{"value":"3","type":"number"}},{"shape_attributes":{"name":"rect","x":945,"y":730,"width":11,"height":23},"region_attributes":{"value":"7","type":"number"}},{"shape_attributes":{"name":"rect","x":954,"y":729,"width":12,"height":22},"region_attributes":{"value":"0","type":"number"}},{"shape_attributes":{"name":"rect","x":967,"y":734,"width":10,"height":18},"region_attributes":{"value":"0","type":"number"}}],"file_attributes":{}},"4_frame12300.jpg565867":{"filename":"4_frame12300.jpg","size":565867,"regions":[{"shape_attributes":{"name":"rect","x":236,"y":734,"width":94,"height":39},"region_attributes":{"value":"na","type":"plate"}},{"shape_attributes":{"name":"rect","x":240,"y":735,"width":12,"height":26},"region_attributes":{"value":"D","type":"alphabet"}},{"shape_attributes":{"name":"rect","x":249,"y":740,"width":9,"height":21},"region_attributes":{"value":"L","type":"alphabet"}},{"shape_attributes":{"name":"rect","x":256,"y":738,"width":11,"height":25},"region_attributes":{"value":"2","type":"number"}},{"shape_attributes":{"name":"rect","x":266,"y":741,"width":9,"height":23},"region_attributes":{"value":"C","type":"alphabet"}},{"shape_attributes":{"name":"rect","x":273,"y":743,"width":10,"height":22},"region_attributes":{"value":"A","type":"alphabet"}},{"shape_attributes":{"name":"rect","x":282,"y":743,"width":8,"height":21},"region_attributes":{"value":"X","type":"alphabet"}},{"shape_attributes":{"name":"rect","x":289,"y":745,"width":9,"height":21},"region_attributes":{"value":"0","type":"number"}},{"shape_attributes":{"name":"rect","x":297,"y":747,"width":10,"height":22},"region_attributes":{"value":"4","type":"number"}},{"shape_attributes":{"name":"rect","x":307,"y":747,"width":8,"height":22},"region_attributes":{"value":"9","type":"number"}},{"shape_attributes":{"name":"rect","x":314,"y":747,"width":10,"height":23},"region_attributes":{"value":"0","type":"number"}},{"shape_attributes":{"name":"rect","x":617,"y":644,"width":30,"height":11},"region_attributes":{"value":"na","type":"plate"}},{"shape_attributes":{"name":"rect","x":872,"y":716,"width":105,"height":21},"region_attributes":{"value":"na","type":"plate"}},{"shape_attributes":{"name":"rect","x":880,"y":717,"width":12,"height":18},"region_attributes":{"value":"U","type":"alphabet"}},{"shape_attributes":{"name":"rect","x":892,"y":719,"width":10,"height":17},"region_attributes":{"value":"P","type":"alphabet"}},{"shape_attributes":{"name":"rect","x":902,"y":717,"width":9,"height":18},"region_attributes":{"value":"1","type":"number"}},{"shape_attributes":{"name":"rect","x":909,"y":718,"width":10,"height":16},"region_attributes":{"value":"4","type":"number"}},{"shape_attributes":{"name":"rect","x":917,"y":715,"width":12,"height":21},"region_attributes":{"value":"D","type":"alphabet"}},{"shape_attributes":{"name":"rect","x":928,"y":717,"width":10,"height":17},"region_attributes":{"value":"D","type":"alphabet"}},{"shape_attributes":{"name":"rect","x":935,"y":716,"width":12,"height":20},"region_attributes":{"value":"3","type":"number"}},{"shape_attributes":{"name":"rect","x":947,"y":719,"width":10,"height":17},"region_attributes":{"value":"7","type":"number"}},{"shape_attributes":{"name":"rect","x":956,"y":716,"width":12,"height":19},"region_attributes":{"value":"0","type":"number"}},{"shape_attributes":{"name":"rect","x":965,"y":718,"width":10,"height":19},"region_attributes":{"value":"0","type":"number"}}],"file_attributes":{}},"4_frame12240.jpg564936":{"filename":"4_frame12240.jpg","size":564936,"regions":[{"shape_attributes":{"name":"rect","x":592,"y":647,"width":30,"height":7},"region_attributes":{"value":"na","type":"plate"}},{"shape_attributes":{"name":"rect","x":882,"y":696,"width":90,"height":23},"region_attributes":{"value":"na","type":"plate"}},{"shape_attributes":{"name":"rect","x":890,"y":700,"width":10,"height":15},"region_attributes":{"value":"U","type":"alphabet"}},{"shape_attributes":{"name":"rect","x":899,"y":702,"width":8,"height":14},"region_attributes":{"value":"P","type":"alphabet"}},{"shape_attributes":{"name":"rect","x":908,"y":702,"width":8,"height":15},"region_attributes":{"value":"1","type":"number"}},{"shape_attributes":{"name":"rect","x":914,"y":700,"width":12,"height":17},"region_attributes":{"value":"4","type":"number"}},{"shape_attributes":{"name":"rect","x":925,"y":701,"width":7,"height":16},"region_attributes":{"value":"D","type":"alphabet"}},{"shape_attributes":{"name":"rect","x":930,"y":699,"width":10,"height":18},"region_attributes":{"value":"D","type":"alphabet"}},{"shape_attributes":{"name":"rect","x":938,"y":698,"width":10,"height":20},"region_attributes":{"value":"3","type":"number"}},{"shape_attributes":{"name":"rect","x":947,"y":701,"width":9,"height":16},"region_attributes":{"value":"7","type":"number"}},{"shape_attributes":{"name":"rect","x":954,"y":701,"width":10,"height":17},"region_attributes":{"value":"0","type":"number"}},{"shape_attributes":{"name":"rect","x":963,"y":700,"width":8,"height":17},"region_attributes":{"value":"0","type":"number"}},{"shape_attributes":{"name":"rect","x":771,"y":642,"width":22,"height":12},"region_attributes":{"value":"na","type":"plate"}}],"file_attributes":{}},"4_frame12180.jpg602746":{"filename":"4_frame12180.jpg","size":602746,"regions":[{"shape_attributes":{"name":"rect","x":84,"y":631,"width":26,"height":13},"region_attributes":{"value":"na","type":"plate"}},{"shape_attributes":{"name":"rect","x":315,"y":679,"width":43,"height":39},"region_attributes":{"value":"na","type":"plate"}},{"shape_attributes":{"name":"rect","x":564,"y":642,"width":37,"height":13},"region_attributes":{"value":"na","type":"plate"}},{"shape_attributes":{"name":"rect","x":780,"y":642,"width":25,"height":7},"region_attributes":{"value":"na","type":"plate"}},{"shape_attributes":{"name":"rect","x":893,"y":692,"width":84,"height":23},"region_attributes":{"value":"na","type":"plate"}},{"shape_attributes":{"name":"rect","x":899,"y":692,"width":12,"height":19},"region_attributes":{"value":"U","type":"alphabet"}},{"shape_attributes":{"name":"rect","x":910,"y":697,"width":7,"height":14},"region_attributes":{"value":"P","type":"alphabet"}},{"shape_attributes":{"name":"rect","x":917,"y":698,"width":8,"height":13},"region_attributes":{"value":"1","type":"number"}},{"shape_attributes":{"name":"rect","x":924,"y":696,"width":10,"height":17},"region_attributes":{"value":"4","type":"number"}},{"shape_attributes":{"name":"rect","x":930,"y":696,"width":10,"height":15},"region_attributes":{"value":"D","type":"alphabet"}},{"shape_attributes":{"name":"rect","x":938,"y":695,"width":9,"height":17},"region_attributes":{"value":"D","type":"alphabet"}},{"shape_attributes":{"name":"rect","x":945,"y":694,"width":10,"height":16},"region_attributes":{"value":"3","type":"number"}},{"shape_attributes":{"name":"rect","x":953,"y":696,"width":7,"height":16},"region_attributes":{"value":"7","type":"number"}},{"shape_attributes":{"name":"rect","x":959,"y":696,"width":10,"height":17},"region_attributes":{"value":"0","type":"number"}},{"shape_attributes":{"name":"rect","x":966,"y":696,"width":10,"height":17},"region_attributes":{"value":"0","type":"number"}}],"file_attributes":{}}}